{"data": [{"count": 0, "id": "17txhj", "title": "Iran shows off new stealth fighter jet, aviation experts mock it as fake. Iran shows new jet flying, turns out to be a toy. ", "score": 2233, "comments": 968, "upvoteRatio": 0.92, "sentiment": -0.07575757575757576}, {"count": 1, "id": "17sxky", "title": "New Saudi fatwah - baby girls must be veiled to stop sexual assault", "score": 1954, "comments": 2592, "upvoteRatio": 0.86, "sentiment": 0.3181818181818182}, {"count": 2, "id": "17tdzj", "title": "Women in Paris are finally allowed to wear trousers, after a 200 year law forbidding them to do so was revoked!", "score": 1881, "comments": 459, "upvoteRatio": 0.89, "sentiment": 0.0}, {"count": 3, "id": "17tecc", "title": "99 Tibetans have self-immolated themselves protesting for independence from China.  Seems like no one has noticed.", "score": 1451, "comments": 344, "upvoteRatio": 0.88, "sentiment": 0.0}, {"count": 4, "id": "17t7ff", "title": "In rush to urbanize, China flattens 700 mountains\n", "score": 857, "comments": 452, "upvoteRatio": 0.93, "sentiment": 0.0}, {"count": 5, "id": "17sz3b", "title": "\nAfter 30 years, is a GM food breakthrough finally here? Golden rice, a new strain that boosts vitamin A levels and reduces blindness in developing countries, is about to be sown in the Philippines\n", "score": 808, "comments": 376, "upvoteRatio": 0.87, "sentiment": 0.14545454545454545}, {"count": 6, "id": "17trpv", "title": "Tens of thousands of black-clad neo-Nazis have rallied in Athens in support of Greece's far-right Golden Dawn party.", "score": 763, "comments": 561, "upvoteRatio": 0.91, "sentiment": 0.3}, {"count": 7, "id": "17t2xy", "title": "The saving of Timbuktu\u2019s priceless manuscripts owes everything to the bravery of an unlikely group \u2014 librarians.", "score": 745, "comments": 79, "upvoteRatio": 0.92, "sentiment": 0.25}, {"count": 8, "id": "17tk19", "title": "To curb rape, Muslim group calls for end to co-ed schools in India", "score": 448, "comments": 288, "upvoteRatio": 0.82, "sentiment": 0.0}, {"count": 9, "id": "17szbb", "title": "Time Running out to Save Elephants from Ivory Trade:  The new wave of killing of elephants in Africa is in many ways far graver than the crisis of the 1970s and 80s. Firstly there are fewer elephants, and secondly the demand for ivory is far higher. ", "score": 299, "comments": 66, "upvoteRatio": 0.9, "sentiment": 0.19090909090909092}]}