{"data": [{"count": 0, "id": "1f1rhd", "title": "Nearly two-thirds of people in the UK believe there will be a 'clash of civilisations' between British Muslims and white Britons", "score": 2209, "comments": 4189, "upvoteRatio": 0.89, "sentiment": 0.03333333333333333}, {"count": 1, "id": "1f0ty6", "title": "Sweden riots spread beyond Stockholm despite extra police", "score": 2202, "comments": 2242, "upvoteRatio": 0.9, "sentiment": 0.0}, {"count": 2, "id": "1f1cmq", "title": "French Soldier stabbed in the neck in Paris, reportedly by man of North African descent.", "score": 2069, "comments": 4318, "upvoteRatio": 0.87, "sentiment": 0.0}, {"count": 3, "id": "1f1vh2", "title": "BBC News - Brazil 'to write off' almost 900M in African debt. \"Brazil has announced that it will cancel or restructure almost $900m (\u00a3600m) worth of debt with Africa.\"", "score": 1992, "comments": 286, "upvoteRatio": 0.94, "sentiment": 0.15}, {"count": 4, "id": "1f0pd1", "title": "Google to bankroll, build wireless networks across Africa, including with balloons, blimps and TV airwaves", "score": 1933, "comments": 307, "upvoteRatio": 0.93, "sentiment": 0.0}, {"count": 5, "id": "1f1447", "title": "Five Undercover Police Cars Sent To Arrest Single Alleged Movie Pirate", "score": 1771, "comments": 349, "upvoteRatio": 0.88, "sentiment": -0.07380952380952381}, {"count": 6, "id": "1f0mjn", "title": "Challenging Monsanto: 200,000 in 40 countries to rally against GMO", "score": 1705, "comments": 807, "upvoteRatio": 0.84, "sentiment": 0.5}, {"count": 7, "id": "1f1cal", "title": "David Simon, creator of The Wire: drug war is \"a holocaust in slow motion\"", "score": 1592, "comments": 176, "upvoteRatio": 0.86, "sentiment": -0.30000000000000004}, {"count": 8, "id": "1f0j7b", "title": "Public rapes outrage Brazil, testing ideas of image and class. 'In one case, an assailant held a gun to the head of a 30-year-old woman while raping her in front of passengers on a bus as the driver proceeded down a main avenue'", "score": 1390, "comments": 254, "upvoteRatio": 0.92, "sentiment": 0.0037037037037036904}, {"count": 9, "id": "1f0vgm", "title": "A suicide bomber has blown herself up close to an interior ministry building in the troubled southern Russian republic of Dagestan, officials say.", "score": 1247, "comments": 327, "upvoteRatio": 0.91, "sentiment": -0.16666666666666666}]}