{"data": [{"count": 0, "id": "1q3moz", "title": "EU rules that gay Africans are entitled to asylum - According to the European Court of Justice, a gay refugee from a country where people are jailed for being homosexual does qualify as a persecuted group eligible for asylum.", "score": 3150, "comments": 1539, "upvoteRatio": 0.94, "sentiment": 0.2777777777777778}, {"count": 1, "id": "1q3g0y", "title": "Islamic Cleric Rapes 4-Year-old Girl on Her First Day at Qur\u2019an School", "score": 2377, "comments": 1689, "upvoteRatio": 0.87, "sentiment": 0.25}, {"count": 2, "id": "1q4tb9", "title": "Woman who cried wolf about rape may have to face her victim in court", "score": 1870, "comments": 1424, "upvoteRatio": 0.86, "sentiment": -0.07500000000000001}, {"count": 3, "id": "1q3f9g", "title": "Gray whale stranded dead with a stomach full of plastic.", "score": 1725, "comments": 256, "upvoteRatio": 0.9, "sentiment": 0.07499999999999998}, {"count": 4, "id": "1q3dru", "title": "Leaked Document Reveals Plot to Destabilize Venezuelan Goverment: \"US Embassy Officials Encouraging Acts of Sabotage\"", "score": 1590, "comments": 412, "upvoteRatio": 0.78, "sentiment": 0.0}, {"count": 5, "id": "1q3fdw", "title": "Legalisation of cannabis motion defeated in Irish Parliament. The motion was defeated 111-8", "score": 1577, "comments": 441, "upvoteRatio": 0.92, "sentiment": 0.0}, {"count": 6, "id": "1q3x58", "title": "Creator of the World Wide Web - Sir Tim Berners-Lee slams governments for 'seriously spying' on the Internet", "score": 1438, "comments": 62, "upvoteRatio": 0.91, "sentiment": -0.21666666666666667}, {"count": 7, "id": "1q2wbu", "title": "New Zealand police are refusing to act on a self-confessed group of gang rapists, but are threatening a man with 6 months in prison for parodying their inaction", "score": 1352, "comments": 99, "upvoteRatio": 0.88, "sentiment": 0.13636363636363635}, {"count": 8, "id": "1q3muu", "title": "UK Gov't Losing The Plot: Now Claiming Snowden Leaks Could Help Pedophiles", "score": 1325, "comments": 215, "upvoteRatio": 0.92, "sentiment": 0.0}, {"count": 9, "id": "1q2eko", "title": "Google has started encrypting traffic between data centers, effectively halting joint surveillance by NSA and GCHQ", "score": 1169, "comments": 127, "upvoteRatio": 0.94, "sentiment": 0.6}]}