{"data": [{"count": 0, "id": "217s2j", "title": "Egypt court sentences 529 to death", "score": 3366, "comments": 1464, "upvoteRatio": 0.95, "sentiment": 0.0}, {"count": 1, "id": "218aq2", "title": "Malayisan PM: \"Flight MH370 ended in the southern Indian Ocean\"", "score": 3295, "comments": 3290, "upvoteRatio": 0.94, "sentiment": 0.0}, {"count": 2, "id": "219lpn", "title": "Solar Power Is Now Just As Cheap As Conventional Electricity In Italy And Germany", "score": 3230, "comments": 812, "upvoteRatio": 0.93, "sentiment": 0.1285714285714286}, {"count": 3, "id": "219brz", "title": "U.S., other powers kick Russia out of G8", "score": 2935, "comments": 3053, "upvoteRatio": 0.9, "sentiment": -0.125}, {"count": 4, "id": "2181ap", "title": "Norway's army is making women share bedrooms with their male colleagues. This has led to a drop in reports of sexual harassment", "score": 2870, "comments": 1023, "upvoteRatio": 0.94, "sentiment": 0.25}, {"count": 5, "id": "218zk9", "title": "Australia, Tony Abbot says, has too much \u201clocked-up forest\u201d. Mr Abbott wants to open up a swathe of Australia\u2019s most fought-over forest and hand it to loggers.", "score": 2347, "comments": 692, "upvoteRatio": 0.93, "sentiment": 0.225}, {"count": 6, "id": "219602", "title": "Qatar 2022 World Cup expected to take more lives than 9/11", "score": 2098, "comments": 345, "upvoteRatio": 0.91, "sentiment": 0.2}, {"count": 7, "id": "216s2t", "title": "Two more colossal pharaoh statues unveiled in Egypt", "score": 1832, "comments": 105, "upvoteRatio": 0.94, "sentiment": 0.4}, {"count": 8, "id": "217gjr", "title": "Poll shows half of Finns would support a military union with Sweden", "score": 1712, "comments": 602, "upvoteRatio": 0.93, "sentiment": -0.13333333333333333}, {"count": 9, "id": "218dah", "title": "Pope Francis announces the first eight members of a new 'commission for safeguarding minors.' One was abused by a priest in the 1960s and has become a prominent activist working to hold the church accountable.", "score": 1003, "comments": 182, "upvoteRatio": 0.91, "sentiment": 0.29545454545454547}]}