{"data": [{"count": 0, "id": "24isxz", "title": "Billionaire dies and leaves $3.3 billion to charity", "score": 3946, "comments": 1887, "upvoteRatio": 0.96, "sentiment": 0.0}, {"count": 1, "id": "24jlt0", "title": "'Many dead' in Ukraine offensive, rebels killed, injured and arrested in Ukraine offensive", "score": 3381, "comments": 2555, "upvoteRatio": 0.95, "sentiment": 0.033333333333333326}, {"count": 2, "id": "24je4i", "title": "Neo-Nazis spark first church alarm since WWII: The churches in J\u00f6nk\u00f6ping, Sweden, rang their bells in warning for two hours on May Day as neo-Nazis took to the streets. The alarm marked the first of its kind for the central Sweden town since World War II broke out.\"", "score": 2581, "comments": 1076, "upvoteRatio": 0.92, "sentiment": 0.24}, {"count": 3, "id": "24jygi", "title": "CBS News Crew Blindfolded, Detained By Pro-Russian Forces In Ukraine", "score": 2470, "comments": 605, "upvoteRatio": 0.92, "sentiment": 0.0}, {"count": 4, "id": "24ieox", "title": "Australia to raise the retirement age to 70", "score": 2397, "comments": 1680, "upvoteRatio": 0.93, "sentiment": 0.0}, {"count": 5, "id": "24kaic", "title": "At least 38 people killed in fire in an official building amid clashes in Odessa, Ukrainian police say", "score": 1934, "comments": 1027, "upvoteRatio": 0.92, "sentiment": -0.25}, {"count": 6, "id": "24i669", "title": "1,000 native women murdered, missing in Canada over 30 years: RCMP", "score": 1794, "comments": 384, "upvoteRatio": 0.91, "sentiment": -0.2}, {"count": 7, "id": "24jntq", "title": "This American Refused to Become an FBI Informant. Then the Government Made His Family's Life Hell.", "score": 1569, "comments": 315, "upvoteRatio": 0.92, "sentiment": 0.0}, {"count": 8, "id": "24jbg8", "title": "Denmark leads the charge in renewable energy | By 2020, the country aims to produce 70 percent of its energy from renewable sources and to make the switch to renewables completely by mid-century. \"Today, we're already at 43 percent,\" said Kristoffer B\u00f6ttzauw", "score": 1454, "comments": 322, "upvoteRatio": 0.91, "sentiment": 0.1}, {"count": 9, "id": "24joj9", "title": "Russia to Ukraine: Your military actions are \u2018criminal\u2019", "score": 913, "comments": 493, "upvoteRatio": 0.9, "sentiment": -0.25}]}