{"data": [{"count": 0, "id": "2xm2tz", "title": "Pakistan Is Arresting People Who Refuse to Vaccinate Their Kids Against Polio", "score": 6801, "comments": 2289, "upvoteRatio": 0.92, "sentiment": 0.0}, {"count": 1, "id": "2xk2sb", "title": "Over 73 percent of Russians admit crisis in Russia", "score": 5125, "comments": 2049, "upvoteRatio": 0.91, "sentiment": 0.0}, {"count": 2, "id": "2xl7v7", "title": "Charlie Hebdo now has 25 times as many subscribers as before deadly attack", "score": 4978, "comments": 1592, "upvoteRatio": 0.88, "sentiment": 0.15}, {"count": 3, "id": "2xj9uk", "title": "Known for his push to legalize cannabis, spartan lifestyle and devotion to his three-legged dog, Uruguay's outspoken President Jose \"Pepe\" Mujica will step down Sunday more popular than ever", "score": 4912, "comments": 972, "upvoteRatio": 0.91, "sentiment": 0.3148148148148148}, {"count": 4, "id": "2xj96u", "title": "Thai temple to build separate toilets for non-Chinese visitors because of the state that Chinese tourists were leaving the toilets in.", "score": 3928, "comments": 1651, "upvoteRatio": 0.94, "sentiment": 0.0}, {"count": 5, "id": "2xjyeb", "title": "More than 70% of UK sex workers used to work in healthcare, education or charities, while more than a third hold university degrees", "score": 3839, "comments": 600, "upvoteRatio": 0.93, "sentiment": 0.3333333333333333}, {"count": 6, "id": "2ximgx", "title": "Lithuania signs US deal to replace Russian gas .", "score": 2885, "comments": 313, "upvoteRatio": 0.94, "sentiment": 0.0}, {"count": 7, "id": "2xkgxo", "title": "Methane Found on Mars, Indicates Life May Once Have Existed There: Nasa", "score": 2508, "comments": 313, "upvoteRatio": 0.92, "sentiment": 0.0}, {"count": 8, "id": "2xk5e0", "title": "Iran says ready to let in Google, other Internet firms", "score": 1923, "comments": 226, "upvoteRatio": 0.92, "sentiment": 0.037500000000000006}, {"count": 9, "id": "2xk2uj", "title": "Thousands in Moscow at Nemtsov march", "score": 1824, "comments": 231, "upvoteRatio": 0.91, "sentiment": 0.0}]}