{"data": [{"count": 0, "id": "34t9m6", "title": "Russian Official Severely Beaten After Reporting Electoral Fraud", "score": 6018, "comments": 1200, "upvoteRatio": 0.92, "sentiment": 0.0}, {"count": 1, "id": "34ryxz", "title": "An estimated 250,000 Bangladeshis, lured with jobs in Malaysia, have been held for ransom in jungle camps by traffickers in Thailand over the last 8 years in a modern day slave trade. Authorities from the three countries are also reportedly involved in the trade.", "score": 5464, "comments": 690, "upvoteRatio": 0.94, "sentiment": 0.1}, {"count": 2, "id": "34ut97", "title": "214 of the 234 girls rescued in Nigeria from Boko Haram are pregnant", "score": 4578, "comments": 1579, "upvoteRatio": 0.93, "sentiment": 0.3333333333333333}, {"count": 3, "id": "34vayy", "title": "Canada's Trudeau vows to cut middle-class taxes, hike taxes on rich", "score": 3998, "comments": 1310, "upvoteRatio": 0.88, "sentiment": 0.375}, {"count": 4, "id": "34rsmh", "title": "Puerto Rico's governor on Sunday signed an executive order authorizing the use of medical marijuana in the U.S. territory in an unexpected move following a lengthy public debate", "score": 3878, "comments": 231, "upvoteRatio": 0.94, "sentiment": 0.025}, {"count": 5, "id": "34udi8", "title": "TransCanada Keystone 1 Pipeline Suffered Major Corrosion Only 2 Yrs in Operation - The cause of the corrosion is being kept from the public by federal regulators & TransCanada.", "score": 3158, "comments": 268, "upvoteRatio": 0.91, "sentiment": 0.020833333333333332}, {"count": 6, "id": "34tr8h", "title": "Germans, still outraged by NSA spying, learn their country may have helped", "score": 3067, "comments": 340, "upvoteRatio": 0.93, "sentiment": -0.9}, {"count": 7, "id": "34tjx6", "title": "An Uphill Campaign in Norway to Promote LSD as a Human Right", "score": 2818, "comments": 679, "upvoteRatio": 0.89, "sentiment": 0.14285714285714285}, {"count": 8, "id": "34uiij", "title": "Nasa captures 17 MILE iceberg break away from West Antarctica's Getz ice shelf", "score": 2176, "comments": 372, "upvoteRatio": 0.91, "sentiment": 0.0}, {"count": 9, "id": "34td7x", "title": "Russian military plane intercepted over Baltic with its transponder switched off", "score": 1921, "comments": 387, "upvoteRatio": 0.89, "sentiment": -0.05}]}