{"data": [{"count": 0, "id": "37utk9", "title": "Boy survives being trapped underwater for 42 minutes. Doctors used a technique called extracorporeal membrane oxygenation to extract oxygen-deprived blood, warm it up and add oxygen, before pumping it back in.", "score": 6276, "comments": 1077, "upvoteRatio": 0.94, "sentiment": 0.13333333333333333}, {"count": 1, "id": "37ttnf", "title": "Paris to remove close to a million \u2018love locks\u2019 left by romantic couples on Pont de Arts bridge", "score": 5000, "comments": 2563, "upvoteRatio": 0.88, "sentiment": 0.16666666666666666}, {"count": 2, "id": "37u202", "title": "7.8 magnitude earthquake shakes buildings in Tokyo", "score": 3458, "comments": 319, "upvoteRatio": 0.92, "sentiment": 0.0}, {"count": 3, "id": "37ua57", "title": "Germany Shines Light on Rape by Troops Who Beat Nazis - New research by a German academic alleges that rape by U.S., British, French and Canadian forces was more commonplace than previously believed.", "score": 2808, "comments": 886, "upvoteRatio": 0.85, "sentiment": 0.10871212121212122}, {"count": 4, "id": "37tv2c", "title": "ISIS committed five million human right abuses in five months", "score": 1641, "comments": 322, "upvoteRatio": 0.88, "sentiment": 0.14285714285714285}, {"count": 5, "id": "37trh6", "title": "Fifa corruption: Sepp Blatter blasts US authorities over investigation", "score": 1136, "comments": 273, "upvoteRatio": 0.9, "sentiment": 0.0}, {"count": 6, "id": "37s58m", "title": "French Constitutional Court rules unconstituional to cut water from people unable to pay, making it effectively unconstitutional to block water access to anyone", "score": 1127, "comments": 248, "upvoteRatio": 0.94, "sentiment": 0.033333333333333326}, {"count": 7, "id": "37t020", "title": "UNESCO heritage experts decide not to list Great Barrier Reef as 'in danger'", "score": 1120, "comments": 104, "upvoteRatio": 0.92, "sentiment": 0.8}, {"count": 8, "id": "37ulck", "title": "India's Air Pollution Is So Bad It's Causing Lung Damage in Kids: In lung tests conducted on 5,718 students, 43.5% suffered from \u201cpoor or restrictive lungs\u201d. About half of the 4.4 million children who live in Delhi have irreversible lung damage.", "score": 863, "comments": 110, "upvoteRatio": 0.92, "sentiment": -0.2825757575757576}, {"count": 9, "id": "37uid6", "title": "Insanity Rules In Ireland: Media Ordered Not To Report On Parliamentary Speech", "score": 802, "comments": 79, "upvoteRatio": 0.92, "sentiment": 0.0}]}