{"data": [{"count": 0, "id": "44j2fl", "title": "North Korea fires long range rocket.", "score": 5961, "comments": 6250, "upvoteRatio": 0.89, "sentiment": -0.05}, {"count": 1, "id": "44o4uh", "title": "Mystery sniper dubbed 'Daesh Hunter' takes out three ISIS terror chiefs in Libyan city - Mirror Online", "score": 5510, "comments": 1562, "upvoteRatio": 0.92, "sentiment": 0.0}, {"count": 2, "id": "44lhtg", "title": "Turkey: Church discovered in world's biggest underground city in Nev\u015fehir with never-before-seen frescos", "score": 5213, "comments": 618, "upvoteRatio": 0.93, "sentiment": 0.0}, {"count": 3, "id": "44mla0", "title": "Indian man could be first recorded human fatality due to a meteorite | Ars Technica", "score": 4311, "comments": 561, "upvoteRatio": 0.94, "sentiment": 0.041666666666666664}, {"count": 4, "id": "44kmks", "title": "China is buying up companies around the world at a record rate", "score": 3655, "comments": 642, "upvoteRatio": 0.92, "sentiment": 0.0}, {"count": 5, "id": "44m7wd", "title": "Swaziland is planning to transfer 18 wild elephants in a Boeing 747 plane to United States in order to relocate them to three American zoos. In exchange, the zoos will be contributing $450,000 to a wildlife conservation trust in Swaziland for rhinos.", "score": 3391, "comments": 284, "upvoteRatio": 0.93, "sentiment": 0.05}, {"count": 6, "id": "44m08c", "title": "Man sells British fresh air to wealthy Chinese elite for \u00a380 a jar", "score": 1743, "comments": 234, "upvoteRatio": 0.91, "sentiment": 0.2}, {"count": 7, "id": "44m4j5", "title": "Another Islamic State jailer who held Western hostages identified as Londoner", "score": 1731, "comments": 418, "upvoteRatio": 0.91, "sentiment": 0.0}, {"count": 8, "id": "44lo9o", "title": "Oil cans as filler material spotted in walls of collapsed Taiwan building may reveal shoddy construction.", "score": 1679, "comments": 200, "upvoteRatio": 0.92, "sentiment": -0.3}, {"count": 9, "id": "44m0as", "title": "Russia is now China's biggest oil partner \u2014 and it's a huge problem for Saudi Arabia", "score": 1662, "comments": 429, "upvoteRatio": 0.92, "sentiment": 0.4000000000000001}]}