{"data": [{"count": 0, "id": "575i7c", "title": "U.S. Navy destroyer again targeted by missiles from Yemen: U.S. officials", "score": 6081, "comments": 2784, "upvoteRatio": 0.9, "sentiment": 0.0}, {"count": 1, "id": "574nu6", "title": "65 thousand Iraqi soldiers ready for Mosul liberation battle", "score": 5976, "comments": 2225, "upvoteRatio": 0.9, "sentiment": 0.2}, {"count": 2, "id": "5730gg", "title": "Woman who survived Isis gang-rape during three months captivity wins prestigious peace prize - Nadia Murad has been presented with the Vaclav Havel Human Rights Prize for her work to protect her Yazidi people from Isis.", "score": 5887, "comments": 1222, "upvoteRatio": 0.86, "sentiment": 0.15}, {"count": 3, "id": "57207n", "title": "Bernie Sanders endorses his brother in race to replace David Cameron", "score": 5298, "comments": 1407, "upvoteRatio": 0.79, "sentiment": 0.0}, {"count": 4, "id": "5755h5", "title": "Pakistan bans Christian TV stations in 'attack on religious freedom' | World | News", "score": 4341, "comments": 663, "upvoteRatio": 0.89, "sentiment": 0.0}, {"count": 5, "id": "57385n", "title": "Australian man Damian Berg cleared by CCTV footage after being 'framed' for Philippines drug deal", "score": 3607, "comments": 287, "upvoteRatio": 0.94, "sentiment": 0.0}, {"count": 6, "id": "5757zj", "title": "The scandal that erupted in the United States over allegations Russia hacked Democratic Party emails has not been in Moscow's interests and both sides in the U.S. election campaign are just using Russia to score points, Vladimir Putin said on Wednesday.", "score": 3542, "comments": 1339, "upvoteRatio": 0.89, "sentiment": 0.0}, {"count": 7, "id": "572wi8", "title": "Scientists accidentally stumble on possible way to slow brain's ageing process", "score": 3269, "comments": 289, "upvoteRatio": 0.93, "sentiment": -0.11666666666666668}, {"count": 8, "id": "571jq3", "title": "Marine fights for Afghan interpreter, a father of 6, to gain entry into US", "score": 2918, "comments": 393, "upvoteRatio": 0.91, "sentiment": 0.0}, {"count": 9, "id": "576awj", "title": "Putin: West responsible for Middle East instability and terrorism in Europe", "score": 2747, "comments": 1069, "upvoteRatio": 0.87, "sentiment": 0.1}]}