{"data": [{"count": 0, "id": "3xokji", "title": "Fifa president Sepp Blatter and Uefa boss Michel Platini have been suspended for eight years from all football-related activities following an ethics investigation.", "score": 14423, "comments": 595, "upvoteRatio": 0.92, "sentiment": 0.0}, {"count": 1, "id": "3xp0yo", "title": "A group of Kenyan Muslims travelling on a bus ambushed by Islamist gunmen protected Christian passengers by refusing to be split into groups, according to eyewitnesses. The bus was travelling from the capital Nairobi to the town of Mandera.", "score": 17273, "comments": 1141, "upvoteRatio": 0.88, "sentiment": 0.0}, {"count": 2, "id": "3xn9ii", "title": "African lions will be added to the endangered species list, activists say", "score": 9294, "comments": 489, "upvoteRatio": 0.91, "sentiment": 0.0}, {"count": 3, "id": "3xpd80", "title": "Wall of Trees Being Planted Across Africa to Halt the Sahara Desert Spreading Farther South", "score": 5020, "comments": 355, "upvoteRatio": 0.92, "sentiment": 0.0}, {"count": 4, "id": "3xntp5", "title": "Minority killings by IS 'should be recognised as genocide", "score": 4347, "comments": 321, "upvoteRatio": 0.91, "sentiment": 0.0}, {"count": 5, "id": "3xpy7b", "title": "ISIS beheads ten of its own militants for escaping battlefield in Mosul", "score": 3870, "comments": 421, "upvoteRatio": 0.92, "sentiment": 0.3}, {"count": 6, "id": "3xnl8b", "title": "Venezuela frees Pepsi workers it arrested for not making enough Pepsi", "score": 3433, "comments": 329, "upvoteRatio": 0.91, "sentiment": 0.0}, {"count": 7, "id": "3xn3ye", "title": "Australian woman, known for her generosity, leaves an amazing legacy by donating her $4.3m fortune to the homeless in her will.", "score": 3256, "comments": 199, "upvoteRatio": 0.89, "sentiment": 0.30000000000000004}, {"count": 8, "id": "3xpkve", "title": "Russia says black box from warplane downed by Turkey unreadable", "score": 2219, "comments": 503, "upvoteRatio": 0.9, "sentiment": -0.16666666666666666}, {"count": 9, "id": "3xq3di", "title": "Six U.S. troops killed outside U.S. airbase by suicide bomber on a motorcycle", "score": 1962, "comments": 738, "upvoteRatio": 0.9, "sentiment": -0.1}, {"count": 10, "id": "3xraqs", "title": "ISIL Leader\u2019s Mobile Phone Shows Turkey\u2019s Support", "score": 1931, "comments": 227, "upvoteRatio": 0.84, "sentiment": 0.0}, {"count": 11, "id": "3xr4fo", "title": "Adolf Hitler's \"Mein Kampf\" to enter public domain on January 1st, 2016", "score": 1914, "comments": 409, "upvoteRatio": 0.9, "sentiment": 0.0}, {"count": 12, "id": "3xqnip", "title": "In leaked tape, ex-Argentine FM says Iran bombed Jewish center", "score": 1032, "comments": 168, "upvoteRatio": 0.81, "sentiment": -0.05}, {"count": 13, "id": "3xqux2", "title": "Bacteria that resist the antibiotic of last resort - colistin - have been discovered in the UK.", "score": 763, "comments": 140, "upvoteRatio": 0.91, "sentiment": 0.0}, {"count": 14, "id": "3xquqt", "title": "Islamic State chief Baghdadi claims he's global leader of Muslims; Pakistan's Taliban says no", "score": 754, "comments": 158, "upvoteRatio": 0.87, "sentiment": 0.0}]}