{"data": [{"count": 0, "id": "4o6uzc", "title": "ISIS Twitter accounts have been hijacked with gay porn", "score": 66151, "comments": 3092, "upvoteRatio": 0.86, "sentiment": 0.4166666666666667}, {"count": 1, "id": "4o5k7d", "title": "Dalai Lama grows quite skeptical about the effects of prayer, stating that serious actions are required for real changes", "score": 26497, "comments": 1921, "upvoteRatio": 0.84, "sentiment": -0.2111111111111111}, {"count": 2, "id": "4o8aqe", "title": "Killing of non-Muslims and minority groups forbidden in Islam.Bangladeshi clerics have issued a fatwa against the killings of minorities and secular campaigners in the mainly Muslim country, where police have arrested over 10,000 people in a crackdown on militancy.", "score": 13737, "comments": 2328, "upvoteRatio": 0.8, "sentiment": 0.16666666666666666}, {"count": 3, "id": "4o5xls", "title": "Nearly 400 international scientists called on Barack Obama to rule out further expansion of oil and gas exploration in Arctic waters under US control.", "score": 7185, "comments": 311, "upvoteRatio": 0.87, "sentiment": 0.03333333333333333}, {"count": 4, "id": "4o8i4g", "title": "LEGO donates 600 million DKK (90.7 million USD) to new children's hospital in Copenhagen", "score": 5945, "comments": 241, "upvoteRatio": 0.92, "sentiment": 0.13636363636363635}, {"count": 5, "id": "4o8k2f", "title": "Physicists have detected ripples in the fabric of spacetime that were set in motion by the collision of two black holes far across the universe more than a billion years ago. The event marks only the second time that scientists have spotted gravitational waves", "score": 5346, "comments": 391, "upvoteRatio": 0.93, "sentiment": 0.08666666666666667}, {"count": 6, "id": "4o8tcz", "title": "Obama meets Dalai Lama in spite of China protest", "score": 4938, "comments": 614, "upvoteRatio": 0.91, "sentiment": 0.0}, {"count": 7, "id": "4o6bda", "title": "Scotland beats climate emissions reductions target six years early. Down 46% since 1990.", "score": 4575, "comments": 136, "upvoteRatio": 0.93, "sentiment": -0.02777777777777779}, {"count": 8, "id": "4oa4mx", "title": "A chilling call: Police to contact 151 Canadians on ISIS 'kill list'", "score": 4270, "comments": 644, "upvoteRatio": 0.92, "sentiment": -0.5}, {"count": 9, "id": "4o9evz", "title": "BBC News: EgyptAir wreckage found in Mediterranean", "score": 2637, "comments": 96, "upvoteRatio": 0.92, "sentiment": 0.0}, {"count": 10, "id": "4o9n95", "title": "India aims for a record by launching 22 satellites on a single rocket", "score": 2165, "comments": 419, "upvoteRatio": 0.9, "sentiment": -0.07142857142857142}, {"count": 11, "id": "4o6nlf", "title": "Israel cuts water supplies to West Bank during Ramadan", "score": 2703, "comments": 1011, "upvoteRatio": 0.69, "sentiment": 0.0}, {"count": 12, "id": "4o5w9t", "title": "Avocado shortage fuels crime wave in New Zealand", "score": 1748, "comments": 329, "upvoteRatio": 0.9, "sentiment": 0.13636363636363635}, {"count": 13, "id": "4o6u0e", "title": "China bans exports of nuclear-use technology to North Korea", "score": 1451, "comments": 67, "upvoteRatio": 0.93, "sentiment": 0.0}, {"count": 14, "id": "4o4mao", "title": "Justin Trudeau considers European troop commitment as Canadian Intel warns Russia is 'mobilizing for war'", "score": 1344, "comments": 911, "upvoteRatio": 0.85, "sentiment": 0.0}]}