{"data": [{"count": 0, "id": "5179hh", "title": "The giant panda is no longer an endangered species, following decades of work by conservationists to save it. The official status of the much-loved animal has been changed from \"endangered\" to \"vulnerable\" because of a population rebound in China.", "score": 46726, "comments": 1720, "upvoteRatio": 0.92, "sentiment": -0.16666666666666666}, {"count": 1, "id": "518v6q", "title": "Philippine President Rodrigo Duterte has warned President Barack Obama not to question him about extrajudicial killings, or \"son of a bitch I will swear at you\" when they meet in Laos during a regional summit.", "score": 26809, "comments": 4637, "upvoteRatio": 0.88, "sentiment": 0.0}, {"count": 2, "id": "51bh8a", "title": "Obama cancels meeting with new Philippine President Duterte", "score": 37819, "comments": 6726, "upvoteRatio": 0.83, "sentiment": 0.13636363636363635}, {"count": 3, "id": "51bctd", "title": "Mexico considers Bill to revoke treaties if Trump wins election", "score": 5964, "comments": 1447, "upvoteRatio": 0.74, "sentiment": 0.3}, {"count": 4, "id": "51a92m", "title": "Philippines president calls Barack Obama 'son of a whore'", "score": 4128, "comments": 812, "upvoteRatio": 0.91, "sentiment": 0.0}, {"count": 5, "id": "519n1h", "title": "Philae found!", "score": 2835, "comments": 131, "upvoteRatio": 0.91, "sentiment": 0.0}, {"count": 6, "id": "51995g", "title": "Screens go blank as Hong Kong election news censored in China", "score": 2109, "comments": 273, "upvoteRatio": 0.93, "sentiment": 0.0}, {"count": 7, "id": "5192lv", "title": "Kiwis want to ditch the Queen as their head of state in favour of a New Zealander, new poll reveals", "score": 1797, "comments": 496, "upvoteRatio": 0.88, "sentiment": 0.13636363636363635}, {"count": 8, "id": "518u7k", "title": "The Isis-US kill ratio is 1-15,000", "score": 1553, "comments": 728, "upvoteRatio": 0.88, "sentiment": 0.0}, {"count": 9, "id": "517qhc", "title": "North Korea fires three ballistic missiles into sea: South Korea", "score": 1076, "comments": 277, "upvoteRatio": 0.89, "sentiment": 0.0}, {"count": 10, "id": "518sy8", "title": "'38 feared dead and 50 injured' after twin explosions rock major Russian naval base", "score": 1065, "comments": 260, "upvoteRatio": 0.87, "sentiment": -0.234375}, {"count": 11, "id": "519so6", "title": "Over 3m Saudi Women Don\u2019t Have ID Cards; Saudi Grand Mufti says portraying the face is forbidden for women, and thus they cannot have ID cards with photos", "score": 966, "comments": 133, "upvoteRatio": 0.84, "sentiment": 0.5}, {"count": 12, "id": "51b6tj", "title": "Soaring ocean temperature is 'greatest hidden challenge of our generation': IUCN report warns that \u2018truly staggering\u2019 rate of warming is changing the behaviour of marine species, reducing fishing zones and spreading disease", "score": 838, "comments": 145, "upvoteRatio": 0.89, "sentiment": 0.4166666666666667}, {"count": 13, "id": "518ime", "title": "Iran Leader\u2019s Message to Muslim World: Muslims Must Understand Blasphemous, Faithless Nature of Saudi Rulers", "score": 814, "comments": 365, "upvoteRatio": 0.9, "sentiment": 0.0}, {"count": 14, "id": "519fmr", "title": "A new generation of pro-democracy activists has won seats on Hong Kong's Legislative Council. The young leaders want greater autonomy and changes to the way Hong Kong is governed by China. Voter turnout reached a record high of 58%.", "score": 633, "comments": 198, "upvoteRatio": 0.89, "sentiment": 0.2240909090909091}]}